akali/__init__.py
akali/augmenter.py
akali/cli.py
akali/config.py
akali/language_interface.py
akali/task_manager.py
akali/utils.py
akali/evaluator/__init__.py
akali/evaluator/evaluator.py
akali/evaluator/criteria/__init__.py
akali/evaluator/criteria/comparison_criteria.py
akali/evaluator/criteria/criteria_factory.py
akali/evaluator/criteria/entity_sentiment_reasoner.py
akali/evaluator/criteria/text_classification.py
akali/models/__init__.py
akali/models/entity_sentiment.py
akali/models/entity_sentiment_reasoner.py
akali/models/text_classification.py
akali/processors/__init__.py
akali/processors/entity_sentiment.py
akali/processors/entity_sentiment_reasoner.py
akali/processors/text_classification.py
akali/training/__init__.py
akali/training/sfftunning_gemma.py
akali-0.3.1b0.dist-info/METADATA
akali-0.3.1b0.dist-info/WHEEL
akali-0.3.1b0.dist-info/entry_points.txt
akali-0.3.1b0.dist-info/top_level.txt
akali-0.3.1b0.dist-info/RECORD
