Metadata-Version: 2.1
Name: akali
Version: 0.3.1b0
Summary: AKALI library for language model augmentation and interfaces
Home-page: https://github.com/alierenak/akali
Author: Ali Eren Ak
Author-email: akali@sabanciuniv.edu
License: Proprietary
Keywords: NLP,language models,data augmentation,AI
Classifier: Development Status :: 4 - Beta
Classifier: Intended Audience :: Developers
Classifier: License :: Other/Proprietary License
Classifier: Operating System :: OS Independent
Classifier: Programming Language :: Python :: 3
Classifier: Programming Language :: Python :: 3.8
Classifier: Programming Language :: Python :: 3.9
Classifier: Programming Language :: Python :: 3.10
Classifier: Topic :: Scientific/Engineering :: Artificial Intelligence
Requires-Python: >=3.8
Requires-Dist: fastapi
Requires-Dist: uvicorn
Requires-Dist: pydantic
Requires-Dist: transformers<5.0.0,>=4.43.1
Requires-Dist: torch
Requires-Dist: accelerate
Requires-Dist: bitsandbytes>=0.39.0
Requires-Dist: nest-asyncio
Requires-Dist: click
Requires-Dist: pandas
Requires-Dist: matplotlib
Provides-Extra: dev
Requires-Dist: pytest<7.0.0,>=6.2.5; extra == "dev"
Requires-Dist: pytest-cov<3.0.0,>=2.12.1; extra == "dev"
Requires-Dist: mypy<1.0.0,>=0.910; extra == "dev"
